<?xml version="1.0" encoding="UTF-8"?>
<site-conf xmlns:xsi="http://www.w3.org/2001/XMLSchema-instance" xsi:noNamespaceSchemaLocation="http://ofbiz.apache.org/dtds/site-conf.xsd">

    <description>Practice Component Site Configuration File</description>
    <owner>Copyright EHE Da Cheng Network Technology Co. LTD.</owner>
    <errorpage>/error/error.jsp</errorpage>
    
    <!-- event handlers -->
    <handler name="java" type="request" class="org.ofbiz.webapp.event.JavaEventHandler"/>
    <handler name="soap" type="request" class="org.ofbiz.webapp.event.SOAPEventHandler"/>
    <handler name="xmlrpc" type="request" class="org.ofbiz.webapp.event.XmlRpcEventHandler"/>
    <handler name="service" type="request" class="org.ofbiz.webapp.event.ServiceEventHandler"/>
    <handler name="ajaxservice" type="request" class="com.ehesys.common.event.AjaxServiceEventHandler" />
    <handler name="service-multi" type="request" class="org.ofbiz.webapp.event.ServiceMultiEventHandler"/>
    <handler name="service-stream" type="request" class="org.ofbiz.webapp.event.ServiceStreamHandler"/>
    <handler name="simple" type="request" class="org.ofbiz.webapp.event.SimpleEventHandler"/>
    <handler name="groovy" type="request" class="org.ofbiz.webapp.event.GroovyEventHandler"/>
    <handler name="rome" type="request" class="org.ofbiz.webapp.event.RomeEventHandler"/>
    <handler name="script" type="request" class="org.ofbiz.webapp.event.ScriptEventHandler"/>

    <!-- view handlers -->
    <handler name="screen" type="view" class="org.ofbiz.widget.screen.MacroScreenViewHandler"/>
    <handler name="screenxml" type="view" class="org.ofbiz.widget.screen.MacroScreenViewHandler"/>
    <handler name="screentext" type="view" class="org.ofbiz.widget.screen.MacroScreenViewHandler"/>
    <handler name="screencsv" type="view" class="org.ofbiz.widget.screen.MacroScreenViewHandler"/>
    <handler name="screenfop" type="view" class="org.ofbiz.widget.screen.ScreenFopViewHandler"/>
    <handler name="jsp" type="view" class="org.ofbiz.webapp.view.JspViewHandler"/>
    <handler name="http" type="view" class="org.ofbiz.webapp.view.HttpViewHandler"/>
    
    <preprocessor>
        <!-- Events to run on every request before security (chains exempt) -->
        <event type="java" path="org.ofbiz.webapp.control.LoginWorker" invoke="checkExternalLoginKey"/>
		
        <!-- <event name="check509CertLogin" type="java" path="org.ofbiz.webapp.control.LoginWorker" invoke="check509CertLogin"/>
        <event name="checkRequestHeaderLogin" type="java" path="org.ofbiz.webapp.control.LoginWorker" invoke="checkRequestHeaderLogin"/>
        <event name="checkServletRequestRemoteUserLogin" type="java" path="org.ofbiz.webapp.control.LoginWorker" invoke="checkServletRequestRemoteUserLogin"/>
        <event name="checkExternalLoginKey" type="java" path="org.ofbiz.webapp.control.LoginWorker" invoke="checkExternalLoginKey"/>
        <event name="checkProtectedView" type="java" path="org.ofbiz.webapp.control.ProtectViewWorker" invoke="checkProtectedView"/>
        <event name="extensionConnectLogin" type="java" path="org.ofbiz.webapp.control.LoginWorker" invoke="extensionConnectLogin"/> -->
		
    </preprocessor> 
    <!-- Request Mappings -->
    

    <!-- login request -->

    
    <!-- <request-map uri="checkLogin" edit="false">
        <description>Verify a user is logged in.</description>
        <security https="true" auth="false"/>
        <event type="java" path="org.ofbiz.webapp.control.LoginWorker" invoke="checkLogin"/>
        <response name="success" type="view" value="main"/>
        <response name="error" type="view" value="login"/>
    </request-map>
    <request-map uri="login"> 
        <security https="true" auth="false"/>
        <event type="java" path="org.ofbiz.webapp.control.LoginWorker" invoke="login"/>
        <response name="success" type="view" value="main"/>
        <response name="error" type="view" value="login"/>
    </request-map>
    <request-map uri="logout">
        <security https="true" auth="false"/>
        <event type="java" path="org.ofbiz.webapp.control.LoginWorker" invoke="logout"/>
        <response name="success" type="none"/>
        <response name="error" type="none" />
    </request-map>
    
     <request-map uri="lastLogin">
        <security https="true" auth="false"/>
        <event type="java" path="com.ehesys.common.login.LastLogin" invoke="lastLogin"/>
        <response name="success" type="none"/>
        <response name="error" type="view"/>
    </request-map> -->
    
    
    
    <!-- View Mappings -->
    <!-- <view-map name="login" type="screen" page="component://ehecommon/widget/CommonScreens.xml#loginForm" />    
	<view-map name="hasNoPermission" type="screen" page="component://ehecommon/widget/CommonScreens.xml#hasNoPermission" /> -->
    <!-- end of view mappings -->
    
    
    <request-map uri="checkLogin" edit="false">
        <description>Verify a user is logged in.</description>
        <security https="true" auth="false"/>
        <event type="java" path="org.ofbiz.webapp.control.LoginWorker" invoke="extensionCheckLogin"/>
        <response name="success" type="view" value="main"/>
        <response name="error" type="view" value="login"/>
    </request-map>
    <request-map uri="login">
        <security https="true" auth="false"/>
        <event type="java" path="org.ofbiz.webapp.control.LoginWorker" invoke="login"/>
        <response name="success" type="view" value="main"/>
        <response name="requirePasswordChange" type="view" value="requirePasswordChange"/>
        <response name="error" type="view" value="login"/>
    </request-map>
    <request-map uri="logout">
        <security https="true" auth="true"/>
        <event type="java" path="org.ofbiz.webapp.control.LoginWorker" invoke="logout"/>
        <response name="success" type="request-redirect" value="main"/>
        <response name="error" type="view" value="main"/>
    </request-map>
    
    
    
    
    <!-- Security Mappings -->
    <request-map uri="checkLogin" edit="false">
        <description>Verify a user is logged in.</description>
        <security https="true" auth="false"/>
        <event type="java" path="org.ofbiz.webapp.control.LoginWorker" invoke="extensionCheckLogin"/>
        <response name="success" type="view" value="main"/>
        <response name="error" type="view" value="login"/>
    </request-map>
    <request-map uri="login">
        <security https="true" auth="false"/>
        <event type="java" path="org.ofbiz.webapp.control.LoginWorker" invoke="login"/>
        <response name="success" type="view" value="main"/>
        <response name="requirePasswordChange" type="view" value="requirePasswordChange"/>
        <response name="error" type="view" value="login"/>
    </request-map>
    <request-map uri="logout">
        <security https="true" auth="true"/>
        <event type="java" path="org.ofbiz.webapp.control.LoginWorker" invoke="logout"/>
        <response name="success" type="request-redirect" value="main"/>
        <response name="error" type="view" value="main"/>
    </request-map>
    <request-map uri="forgotPassword">
        <security https="true" auth="false"/>
        <event type="java" path="org.ofbiz.securityext.login.LoginEvents" invoke="forgotPassword"/>
        <response name="success" type="view" value="forgotPassword"/>
        <response name="error" type="view" value="forgotPassword"/>
    </request-map>
    <request-map uri="passwordChange">
        <security https="true" auth="false"/>
        <response name="success" type="view" value="requirePasswordChange"/>
    </request-map>
    
    <!--========================== AJAX events =====================-->

    <!-- View Mappings -->
    <view-map name="error" page="/error/error.jsp"/>
    <view-map name="main" type="none"/>
    <view-map name="login" type="screen" page="component://saasbase/widget/CommonScreens.xml#login"/>
    
    
</site-conf>